polly_validator/__init__.py
polly_validator/config.py
polly_validator/settings.py
polly_validator/downloader/__init__.py
polly_validator/downloader/get_valid_names.py
polly_validator/utility/__init__.py
polly_validator/utility/build_job_json.py
polly_validator/utility/errors.py
polly_validator/utility/helper.py
polly_validator/validators/__init__.py
polly_validator/validators/dataset_metadata_validator.py
polly_validator/validators/run_validator_repo_wise.py
polly_validator/validators/sample_metadata_validator.py
polly_validator/validators/schema_constructors/__init__.py
polly_validator/validators/schema_constructors/dataset_level.py
polly_validator/validators/schema_constructors/sample_level.py
polly_validator-0.0.2.dist-info/LICENSE.md
polly_validator-0.0.2.dist-info/METADATA
polly_validator-0.0.2.dist-info/WHEEL
polly_validator-0.0.2.dist-info/top_level.txt
polly_validator-0.0.2.dist-info/RECORD
