Metadata-Version: 2.1
Name: polly-validator
Version: 0.0.2
Summary: Data Validation Library
Author: Sanchit Verma
License-File: LICENSE.md
Requires-Dist: appdirs (==1.4.4)
Requires-Dist: pandas
Requires-Dist: pydantic
Requires-Dist: rapidfuzz (==2.1.1)
Requires-Dist: requests (==2.25.1)
Requires-Dist: tabulate (==0.8.10)
Requires-Dist: pronto
